
{
    "user1": {
        "user": "xxx",
        "tester": "ives",
        "email": "profile1@gmail.com",
        "password": "ppppp",
        "remark": "stg"
    },
    "user2": {
        "user": "",
        "tester": "ives",
        "email": "profile2@gmail.com",
        "password": "ppppp",
        "remark": "dev"
    },
    "user3": {
        "user": "",
        "tester": "ives",
        "email": "profile3@gmail.com",
        "password": "ppppp",
        "remark": "prod"
    },
    "user4": {
        "user": "",
        "tester": "automation",
        "email": "profile4@gmail.com",
        "password": "ppppp",
        "remark": "prod"
    }
}

